client/__init__.py
client/api.py
client/country_data.py
client/launcher.py
client/main.py
client/ror_loader.py
client/settings.py
tlscouting-0.4.0.dist-info/METADATA
tlscouting-0.4.0.dist-info/WHEEL
tlscouting-0.4.0.dist-info/entry_points.txt
tlscouting-0.4.0.dist-info/RECORD
