Metadata-Version: 2.4
Name: TLScouting
Version: 0.4.0
Summary: Scouting Database for TandemLaunch's Active Recruitment
Requires-Python: >=3.12
Requires-Dist: platformdirs>=4.3.7
Requires-Dist: pycountry>=24.6.1
Requires-Dist: pyqt6>=6.9.0
Requires-Dist: requests>=2.32.3
Requires-Dist: tomli-w>=1.2.0
Requires-Dist: tomli>=2.2.1
Provides-Extra: server
Requires-Dist: fastapi>=0.115.0; extra == 'server'
Requires-Dist: pydantic[email]>=2.11.0; extra == 'server'
Requires-Dist: uvicorn>=0.34.0; extra == 'server'
